adddi/__init__.py
adddi/test.py
adddi_test-0.0.1.dist-info/METADATA
adddi_test-0.0.1.dist-info/WHEEL
adddi_test-0.0.1.dist-info/top_level.txt
adddi_test-0.0.1.dist-info/RECORD
